deshima_sensitivity/__init__.py
deshima_sensitivity/atmosphere.py
deshima_sensitivity/data/atm.csv
deshima_sensitivity/data/z_Dl.csv
deshima_sensitivity/filter.py
deshima_sensitivity/galaxy.py
deshima_sensitivity/instruments.py
deshima_sensitivity/physics.py
deshima_sensitivity/plotting.py
deshima_sensitivity/simulator.py
deshima_sensitivity-0.4.2.dist-info/LICENSE
deshima_sensitivity-0.4.2.dist-info/METADATA
deshima_sensitivity-0.4.2.dist-info/WHEEL
deshima_sensitivity-0.4.2.dist-info/RECORD
