Metadata-Version: 2.1
Name: deshima-sensitivity
Version: 0.4.2
Summary: Sensitivity calculator for DESHIMA-type spectrometers
Home-page: https://github.com/deshima-dev/deshima-sensitivity
License: MIT
Author: Akira Endo
Author-email: a.endo@tudelft.nl
Maintainer: Akio Taniguchi
Maintainer-email: taniguchi@a.phys.nagoya-u.ac.jp
Requires-Python: >=3.7.1,<3.11
Classifier: License :: OSI Approved :: MIT License
Classifier: Programming Language :: Python :: 3
Classifier: Programming Language :: Python :: 3.8
Classifier: Programming Language :: Python :: 3.9
Classifier: Programming Language :: Python :: 3.10
Requires-Dist: jupyter-io (>=0.2,<0.3)
Requires-Dist: lmfit (>=1.0,<2.0)
Requires-Dist: matplotlib (>=3.2,<4.0)
Requires-Dist: numpy (>=1.20,<1.22) ; python_full_version >= "3.7.1" and python_version < "3.8"
Requires-Dist: numpy (>=1.20,<2.0) ; python_version >= "3.8" and python_version < "3.11"
Requires-Dist: pandas (>=1.3,<1.4) ; python_full_version >= "3.7.1" and python_version < "3.8"
Requires-Dist: pandas (>=1.3,<2.0) ; python_version >= "3.8" and python_version < "3.11"
Requires-Dist: pandas-dataclasses (>=0.2,<0.3)
Requires-Dist: scipy (>=1.4,<2.0)
Project-URL: Documentation, https://deshima-dev.github.io/deshima-sensitivity/
